ssqll/__init__.py
ssqll/tests/args_test.py
ssqll/tests/sample-uk.db
ssqll/tests/sql_test.py
Sentosa_SQL_Library-0.2.dist-info/LICENSE
Sentosa_SQL_Library-0.2.dist-info/METADATA
Sentosa_SQL_Library-0.2.dist-info/WHEEL
Sentosa_SQL_Library-0.2.dist-info/top_level.txt
Sentosa_SQL_Library-0.2.dist-info/RECORD
